{
  "status": "blocked",
  "blockers": [
    {
      "blocker_id": "full_57_ready_action_business_input_execution_not_complete",
      "description": "Full 57 ready Core action business-input execution and per-action artifact assertions are not complete.",
      "status": "remaining"
    },
    {
      "blocker_id": "rag_retrieval_verification_smoke_review_required",
      "description": "Claim verification is not claimed as fully real without prepared business assertions.",
      "status": "remaining"
    },
    {
      "blocker_id": "agent_factory_runtime_smoke_review_required",
      "description": "Runtime trace is deterministic smoke until full local user tasks are asserted.",
      "status": "remaining"
    }
  ]
}
