{
    "schema_version":  "marker.dependency_remediation.v1",
    "adapter_name":  "marker",
    "install_attempted":  true,
    "install_command":  "python -m pip install marker-pdf\u003e=1,\u003c2",
    "installed_version":  "1.10.2",
    "source":  "PyPI: marker-pdf; runtime CLI: marker_single",
    "install_path":  "D:\\HeiTang-Codex-WorkSpace\\Project_01_HeiTang_KB_Forge\\kb-forge-skill\\_local_dependency_remediation\\marker",
    "risk":  [
                 "Marker and Surya model assets require several gigabytes of local storage.",
                 "Marker licensing acceptance is a separate product gate and is not treated as a runtime failure.",
                 "Runtime success does not prove portable EXE bundling."
             ],
    "rollback_plan":  [
                          "Remove the isolated Marker environment if the remediation must be reverted.",
                          "Point HEITANG_MARKER_MODEL_CACHE back to an approved retained cache copy.",
                          "Do not delete the legacy datalab cache until a separate cleanup checkpoint is accepted."
                      ],
    "post_install_check_result":  "available",
    "post_install_smoke_result":  "pass",
    "runtime_status":  "available",
    "smoke_status":  "passed",
    "license_gate_status":  "license_gate_pending",
    "final_decision":  "real_integration",
    "old_cache_path":  "C:\\Users\\Administrator\\AppData\\Local\\datalab\\datalab\\Cache",
    "old_model_cache_path":  "C:\\Users\\Administrator\\AppData\\Local\\datalab\\datalab\\Cache\\models",
    "new_cache_path":  "D:\\HeiTang-Codex-WorkSpace\\Project_01_HeiTang_KB_Forge\\kb-forge-skill\\_local_dependency_remediation\\marker\\model_cache",
    "cache_size":  {
                       "old_bytes":  3447389424,
                       "new_bytes":  3447389424
                   },
    "migration_needed":  false,
    "cleanup_suggestion":  "Retain the old cache until workspace-local Markdown and JSON smokes pass and file counts/sizes are verified; then use the documented cleanup plan instead of automatic deletion.",
    "blocker_evidence":  null,
    "migration_performed":  true
}
